byteplug_endpoints-0.1.1-nspkg.pth
byteplug/endpoints/__init__.py
byteplug/endpoints/endpoint.py
byteplug/endpoints/endpoints.py
byteplug/endpoints/exception.py
byteplug/endpoints/record.py
byteplug/endpoints/specs.py
byteplug/endpoints/utils.py
byteplug_endpoints-0.1.1.dist-info/LICENSE.txt
byteplug_endpoints-0.1.1.dist-info/METADATA
byteplug_endpoints-0.1.1.dist-info/WHEEL
byteplug_endpoints-0.1.1.dist-info/namespace_packages.txt
byteplug_endpoints-0.1.1.dist-info/top_level.txt
byteplug_endpoints-0.1.1.dist-info/RECORD
